LICENSE
MANIFEST.in
README.rst
setup.py
mezzanine_dpaste.egg-info/PKG-INFO
mezzanine_dpaste.egg-info/SOURCES.txt
mezzanine_dpaste.egg-info/dependency_links.txt
mezzanine_dpaste.egg-info/requires.txt
mezzanine_dpaste.egg-info/top_level.txt
mezzpaste/__init__.py
mezzpaste/urls.py
mezzpaste/views.py
mezzpaste/static/mezzpaste/css/mezzpaste.css
mezzpaste/templates/dpaste/base.html
mezzpaste/templates/dpaste/snippet_details.html
mezzpaste/templates/dpaste/snippet_form.html
mezzpaste/templates/dpaste/snippet_new.html
mezzpaste/templates/dpaste/snippet_pre.html
mezzpaste/templates/mezzpaste/includes/stats_panel.html
mezzpaste/templatetags/__init__.py
mezzpaste/templatetags/mezzpaste_filters.py
mezzpaste/templatetags/mezzpaste_tags.py