Metadata-Version: 1.1
Name: mezzanine-dpaste
Version: 1.1.1
Summary: A Mezzanine app to integrate dpaste, a Django pastebin.
Home-page: http://github.com/prikhi/mezzanine-dpaste
Author: Pavan Rikhi
Author-email: pavan@sleepanarchy.com
License: GPLv3
Platform: UNKNOWN
Classifier: Development Status :: 5 - Production/Stable
Classifier: Environment :: Web Environment
Classifier: Framework :: Django
Classifier: Intended Audience :: Developers
Classifier: License :: OSI Approved :: GNU General Public License v3 (GPLv3)
Classifier: Operating System :: OS Independent
Classifier: Programming Language :: Python
Classifier: Topic :: Internet :: WWW/HTTP
